MANIFEST.in
README.md
requirements.txt
setup.cfg
setup.py
regression/__init__.py
regression/algorithms.py
regression/model.py
regression/utils.py
test/test_regression.py
thunder_regression.egg-info/PKG-INFO
thunder_regression.egg-info/SOURCES.txt
thunder_regression.egg-info/dependency_links.txt
thunder_regression.egg-info/requires.txt
thunder_regression.egg-info/top_level.txt