Metadata-Version: 1.0
Name: thunder-regression
Version: 1.0.0
Summary: algorithms for mass univariate regression
Home-page: https://github.com/freeman-lab/thunder-regression
Author: jwittenbach
Author-email: the.freeman.lab@gmail.com
License: MIT
Platform: UNKNOWN
